README.md
setup.py
bit/__init__.py
bit/base32.py
bit/base58.py
bit/cli.py
bit/constants.py
bit/crypto.py
bit/curve.py
bit/exceptions.py
bit/format.py
bit/keygen.py
bit/transaction.py
bit/utils.py
bit/wallet.py
bit/network/__init__.py
bit/network/fees.py
bit/network/meta.py
bit/network/rates.py
bit/network/services.py
pity.egg-info/PKG-INFO
pity.egg-info/SOURCES.txt
pity.egg-info/dependency_links.txt
pity.egg-info/entry_points.txt
pity.egg-info/requires.txt
pity.egg-info/top_level.txt
tests/__init__.py
tests/samples.py
tests/test_base58.py
tests/test_curve.py
tests/test_format.py
tests/test_segwit_addr.py
tests/test_transaction.py
tests/test_utils.py
tests/test_wallet.py
tests/utils.py
tests/network/__init__.py
tests/network/test_fees.py
tests/network/test_meta.py
tests/network/test_rates.py
tests/network/test_services.py