Metadata-Version: 2.1
Name: pity
Version: 0.5.1
Summary: Peercoin made easy.
Home-page: https://github.com/peercoin/pity
Author: Peerchemist
Author-email: peerchemist@protonmail.ch
License: MIT
Download-URL: https://github.com/peercoin/pity
Keywords: peercoin,cryptocurrency,payments,tools,wallet
Platform: UNKNOWN
Classifier: Development Status :: 4 - Beta
Classifier: Intended Audience :: Developers
Classifier: Intended Audience :: End Users/Desktop
Classifier: License :: OSI Approved :: MIT License
Classifier: Natural Language :: English
Classifier: Operating System :: OS Independent
Classifier: Programming Language :: Python :: 3.5
Classifier: Programming Language :: Python :: 3.6
Classifier: Programming Language :: Python :: 3.7
Classifier: Programming Language :: Python :: Implementation :: CPython
Classifier: Programming Language :: Python :: Implementation :: PyPy
Provides-Extra: cache
Provides-Extra: cli
